setup.py
maxquant/__init__.py
maxquant/analysis.py
maxquant/annotations.py
maxquant/filters.py
maxquant/imputation.py
maxquant/io.py
maxquant/normalization.py
maxquant/process.py
maxquant/visualize.py
pyMaxQuant.egg-info/PKG-INFO
pyMaxQuant.egg-info/SOURCES.txt
pyMaxQuant.egg-info/dependency_links.txt
pyMaxQuant.egg-info/requires.txt
pyMaxQuant.egg-info/top_level.txt