Metadata-Version: 1.1
Name: pyMaxQuant
Version: 0.1.0
Summary: A Python interface for working with MaxQuant & Perseus outputs
Home-page: http://github.com/mfitzp/pymaxquant
Author: Martin Fitzpatrick
Author-email: martin.fitzpatrick@gmail.com
License: MIT
Platform: UNKNOWN
Classifier: Development Status :: 2 - Pre-Alpha
Classifier: Intended Audience :: Developers
Classifier: Topic :: Desktop Environment
Classifier: Topic :: Software Development :: Build Tools
Classifier: Topic :: Software Development :: Widget Sets
Classifier: Programming Language :: Python :: 2.7
Classifier: Programming Language :: Python :: 3.4
